odoo/addons/stock_operating_unit/README.rst
odoo/addons/stock_operating_unit/__init__.py
odoo/addons/stock_operating_unit/__manifest__.py
odoo/addons/stock_operating_unit/hooks.py
odoo/addons/stock_operating_unit/data/stock_data.xml
odoo/addons/stock_operating_unit/demo/stock_demo.xml
odoo/addons/stock_operating_unit/i18n/pt.po
odoo/addons/stock_operating_unit/i18n/stock_operating_unit.pot
odoo/addons/stock_operating_unit/models/__init__.py
odoo/addons/stock_operating_unit/models/product_product.py
odoo/addons/stock_operating_unit/models/stock_location.py
odoo/addons/stock_operating_unit/models/stock_move.py
odoo/addons/stock_operating_unit/models/stock_picking.py
odoo/addons/stock_operating_unit/models/stock_rule.py
odoo/addons/stock_operating_unit/models/stock_warehouse.py
odoo/addons/stock_operating_unit/readme/CONFIGURE.rst
odoo/addons/stock_operating_unit/readme/CONTRIBUTORS.rst
odoo/addons/stock_operating_unit/readme/DESCRIPTION.rst
odoo/addons/stock_operating_unit/readme/ROADMAP.rst
odoo/addons/stock_operating_unit/readme/USAGE.rst
odoo/addons/stock_operating_unit/security/stock_security.xml
odoo/addons/stock_operating_unit/static/description/icon.png
odoo/addons/stock_operating_unit/static/description/index.html
odoo/addons/stock_operating_unit/tests/__init__.py
odoo/addons/stock_operating_unit/tests/test_stock_operating_unit.py
odoo/addons/stock_operating_unit/tests/test_stock_picking.py
odoo/addons/stock_operating_unit/tests/test_stock_security.py
odoo/addons/stock_operating_unit/view/stock.xml
odoo/addons/stock_operating_unit/view/stock_picking.xml
odoo12_addon_stock_operating_unit-12.0.2.0.0.dist-info/METADATA
odoo12_addon_stock_operating_unit-12.0.2.0.0.dist-info/WHEEL
odoo12_addon_stock_operating_unit-12.0.2.0.0.dist-info/top_level.txt
odoo12_addon_stock_operating_unit-12.0.2.0.0.dist-info/RECORD
